{"assets/fonts/Berkshire Swash.ttf":["assets/fonts/Berkshire Swash.ttf"],"assets/images/bookly_app.jpg":["assets/images/bookly_app.jpg"],"assets/images/boutique_app.jpg":["assets/images/boutique_app.jpg"],"assets/images/github.svg":["assets/images/github.svg"],"assets/images/hm.svg":["assets/images/hm.svg"],"assets/images/home.png":["assets/images/home.png"],"assets/images/lin.svg":["assets/images/lin.svg"],"assets/images/me.jpg":["assets/images/me.jpg"],"assets/images/movie_zone.jpg":["assets/images/movie_zone.jpg"],"assets/images/note_app.jpeg":["assets/images/note_app.jpeg"],"assets/images/vital_heal.jpg":["assets/images/vital_heal.jpg"],"assets/images/weather_app.jpg":["assets/images/weather_app.jpg"],"packages/cupertino_icons/assets/CupertinoIcons.ttf":["packages/cupertino_icons/assets/CupertinoIcons.ttf"]}